jsonschema/__init__.py
jsonschema/__main__.py
jsonschema/_format.py
jsonschema/_keywords.py
jsonschema/_legacy_keywords.py
jsonschema/_types.py
jsonschema/_typing.py
jsonschema/_utils.py
jsonschema/cli.py
jsonschema/exceptions.py
jsonschema/protocols.py
jsonschema/validators.py
jsonschema/benchmarks/__init__.py
jsonschema/benchmarks/const_vs_enum.py
jsonschema/benchmarks/contains.py
jsonschema/benchmarks/import_benchmark.py
jsonschema/benchmarks/issue232.py
jsonschema/benchmarks/json_schema_test_suite.py
jsonschema/benchmarks/nested_schemas.py
jsonschema/benchmarks/subcomponents.py
jsonschema/benchmarks/unused_registry.py
jsonschema/benchmarks/useless_applicator_schemas.py
jsonschema/benchmarks/useless_keywords.py
jsonschema/benchmarks/validator_creation.py
jsonschema/benchmarks/issue232/issue.json
jsonschema/tests/__init__.py
jsonschema/tests/_suite.py
jsonschema/tests/fuzz_validate.py
jsonschema/tests/test_cli.py
jsonschema/tests/test_deprecations.py
jsonschema/tests/test_exceptions.py
jsonschema/tests/test_format.py
jsonschema/tests/test_jsonschema_test_suite.py
jsonschema/tests/test_types.py
jsonschema/tests/test_utils.py
jsonschema/tests/test_validators.py
jsonschema/tests/typing/__init__.py
jsonschema/tests/typing/test_all_concrete_validators_match_protocol.py
jsonschema_utf8-4.1.0.dist-info/METADATA
jsonschema_utf8-4.1.0.dist-info/WHEEL
jsonschema_utf8-4.1.0.dist-info/entry_points.txt
jsonschema_utf8-4.1.0.dist-info/licenses/COPYING
jsonschema_utf8-4.1.0.dist-info/RECORD
