Metadata-Version: 2.4
Name: jsonschema-utf8
Version: 4.1.0
Summary: An implementation of JSON Schema validation for Python with support for utf8. A fork of jsonschema.
Project-URL: Homepage, https://github.com/wongtimn5-d/jsonschema-utf8
Project-URL: Documentation, https://python-jsonschema.readthedocs.io/
Project-URL: Issues, https://github.com/wongtimn5-d/jsonschema-utf8/issues/
Project-URL: Funding, https://github.com/sponsors/Julian
Project-URL: Changelog, https://github.com/wongtimn5-d/jsonschema-utf8/blob/main/CHANGELOG.rst
Project-URL: Source, https://github.com/wongtimn5-d/jsonschema-utf8
Author-email: Tim Wong <wongtimn5@gmail.com>
License-Expression: MIT
License-File: COPYING
Keywords: data validation,json,json schema,jsonschema,validation
Classifier: Development Status :: 5 - Production/Stable
Classifier: Intended Audience :: Developers
Classifier: Operating System :: OS Independent
Classifier: Programming Language :: Python
Classifier: Programming Language :: Python :: 3.10
Classifier: Programming Language :: Python :: 3.11
Classifier: Programming Language :: Python :: 3.12
Classifier: Programming Language :: Python :: 3.13
Classifier: Programming Language :: Python :: 3.14
Classifier: Programming Language :: Python :: Implementation :: CPython
Classifier: Programming Language :: Python :: Implementation :: PyPy
Classifier: Topic :: File Formats :: JSON
Classifier: Topic :: File Formats :: JSON :: JSON Schema
Requires-Python: >=3.10
Requires-Dist: attrs>=22.2.0
Requires-Dist: jsonschema-specifications>=2023.03.6
Requires-Dist: referencing>=0.28.4
Requires-Dist: rpds-py>=0.25.0
Provides-Extra: format
Requires-Dist: fqdn; extra == 'format'
Requires-Dist: idna; extra == 'format'
Requires-Dist: isoduration; extra == 'format'
Requires-Dist: jsonpointer>1.13; extra == 'format'
Requires-Dist: rfc3339-validator; extra == 'format'
Requires-Dist: rfc3987; extra == 'format'
Requires-Dist: uri-template; extra == 'format'
Requires-Dist: webcolors>=1.11; extra == 'format'
Provides-Extra: format-nongpl
Requires-Dist: fqdn; extra == 'format-nongpl'
Requires-Dist: idna; extra == 'format-nongpl'
Requires-Dist: isoduration; extra == 'format-nongpl'
Requires-Dist: jsonpointer>1.13; extra == 'format-nongpl'
Requires-Dist: rfc3339-validator; extra == 'format-nongpl'
Requires-Dist: rfc3986-validator>0.1.0; extra == 'format-nongpl'
Requires-Dist: rfc3987-syntax>=1.1.0; extra == 'format-nongpl'
Requires-Dist: uri-template; extra == 'format-nongpl'
Requires-Dist: webcolors>=24.6.0; extra == 'format-nongpl'
